zhihu_oauth/__init__.py
zhihu_oauth/client.py
zhihu_oauth/exception.py
zhihu_oauth/helpers.py
zhihu_oauth/setting.py
zhihu_oauth/utils.py
zhihu_oauth/oauth/__init__.py
zhihu_oauth/oauth/before_login_auth.py
zhihu_oauth/oauth/im_android.py
zhihu_oauth/oauth/setting.py
zhihu_oauth/oauth/token.py
zhihu_oauth/oauth/utils.py
zhihu_oauth/oauth/zhihu_oauth.py
zhihu_oauth/zhcls/__init__.py
zhihu_oauth/zhcls/activity.py
zhihu_oauth/zhcls/answer.py
zhihu_oauth/zhcls/article.py
zhihu_oauth/zhcls/base.py
zhihu_oauth/zhcls/collection.py
zhihu_oauth/zhcls/column.py
zhihu_oauth/zhcls/comment.py
zhihu_oauth/zhcls/feed.py
zhihu_oauth/zhcls/generator.py
zhihu_oauth/zhcls/live.py
zhihu_oauth/zhcls/me.py
zhihu_oauth/zhcls/message.py
zhihu_oauth/zhcls/normal.py
zhihu_oauth/zhcls/other.py
zhihu_oauth/zhcls/people.py
zhihu_oauth/zhcls/pin.py
zhihu_oauth/zhcls/question.py
zhihu_oauth/zhcls/search.py
zhihu_oauth/zhcls/streaming.py
zhihu_oauth/zhcls/topic.py
zhihu_oauth/zhcls/urls.py
zhihu_oauth/zhcls/utils.py
zhihu_oauth/zhcls/whisper.py
zhihu_oauth-0.0.42.dist-info/LICENSE
zhihu_oauth-0.0.42.dist-info/METADATA
zhihu_oauth-0.0.42.dist-info/WHEEL
zhihu_oauth-0.0.42.dist-info/top_level.txt
zhihu_oauth-0.0.42.dist-info/RECORD
