Metadata-Version: 2.1
Name: zhihu-oauth
Version: 0.0.42
Summary: 尝试解析出知乎官方未开放的 OAuth2 接口，并提供优雅的使用方式，作为 zhihu-py3 项目的替代者
Home-page: https://git.7sdre.am/7sDream/zhihu-oauth
Author: 7sDream
Author-email: 7seconddream@gmail.com
License: MIT
Keywords: zhihu,network,http,OAuth,JSON
Platform: UNKNOWN
Classifier: Development Status :: 3 - Alpha
Classifier: Environment :: Web Environment
Classifier: Intended Audience :: Developers
Classifier: License :: OSI Approved :: MIT License
Classifier: Operating System :: OS Independent
Classifier: Programming Language :: Python
Classifier: Programming Language :: Python :: 2.7
Classifier: Programming Language :: Python :: 3.5
Classifier: Programming Language :: Python :: 3.6
Classifier: Programming Language :: Python :: 3.7
Classifier: Programming Language :: Python :: 3.8
Classifier: Programming Language :: Python :: 3.9
Classifier: Topic :: Internet :: WWW/HTTP
Classifier: Topic :: Software Development :: Libraries :: Python Modules
Requires-Dist: requests (>=2.10.0)
